demand_sigmoid/__init__.py
demand_sigmoid/demand_sigmoid.py
demand_sigmoid-0.1.6.dist-info/METADATA
demand_sigmoid-0.1.6.dist-info/WHEEL
demand_sigmoid-0.1.6.dist-info/top_level.txt
demand_sigmoid-0.1.6.dist-info/RECORD
